{"additional_card-mod.md":"n63CNRiy","additional_javascript-template.md":"BWvP9hhK","additional_migration-to-material.md":"nvhLp283","additional_using-the-icon-property.md":"CKY_qCnd","cards_material-alarm-card.md":"BwuSz4wl","cards_material-button-card.md":"Dop5m8oW","cards_material-circle-progress-card.md":"DR0ik_Io","cards_material-climate-card.md":"BhvNBVrn","cards_material-control-card.md":"TS2VX3l1","cards_material-dashboard-card.md":"D5BrOcy8","cards_material-dialog-card.md":"rog4GiQa","cards_material-lights-card.md":"Bw4i0NUB","cards_material-menu-card.md":"jcIaCqsX","cards_material-options-card.md":"VSTgwzkJ","cards_material-popup-card.md":"Dug_hs3Y","cards_material-slider-card.md":"B5fCYp-7","cards_material-users-card.md":"_1eNVKGv","dialogs_material-alarm-dialog.md":"BVZbrvnI","dialogs_material-battery-dialog.md":"CAVWJF5s","dialogs_material-light-switch-dialog.md":"BDIn5AYB","dialogs_material-media-page.md":"FqK5YaYi","dialogs_material-sensor-dialog.md":"CeB5VKHF","index.md":"fMnkNR5b","setup_installation.md":"5uirjcP3","setup_overview.md":"tDSJ6nzF","setup_preview.md":"B9Qu0hdZ","setup_requirements.md":"MaF9OIj7"}
