{"cards_material-button-card.md":"BN_pZcf_","cards_material-climate-card.md":"DXryQg_B","cards_material-control-card.md":"Cvg1cwoy","cards_material-dashboard-card.md":"xfac0XBU","cards_material-dialog-page.md":"Gczyzuj1","cards_material-light-card.md":"hwSohrvc","cards_material-option-card.md":"CO-ay3DU","cards_material-popup-card.md":"-c9V-6Yx","cards_material-slider-card.md":"DZ-k_W6C","index.md":"DCmS3fyn","setup_installation.md":"5uirjcP3","setup_overview.md":"Xd4AMMkL","setup_preview.md":"D8LI8mhg","setup_requirements.md":"Duk0xsqP"}
